dgraphrag/__init__.py
dgraphrag/cli.py
dgraphrag/core/__init__.py
dgraphrag/core/base.py
dgraphrag/core/exceptions.py
dgraphrag/graph/__init__.py
dgraphrag/graph/adapters.py
dgraphrag/graph/adapters_arangodb.py
dgraphrag/graph/adapters_neo4j.py
dgraphrag/graph/adapters_tigergraph.py
dgraphrag/graph/builders.py
dgraphrag/graph/indexers.py
dgraphrag/ingestion/__init__.py
dgraphrag/ingestion/extractors.py
dgraphrag/ingestion/extractors_advanced.py
dgraphrag/ingestion/loaders.py
dgraphrag/ingestion/splitters.py
dgraphrag/retrieval/__init__.py
dgraphrag/retrieval/advanced_retrievers.py
dgraphrag/retrieval/graph_retrievers.py
dgraphrag-0.0.3.dist-info/licenses/LICENSE
dgraphrag-0.0.3.dist-info/METADATA
dgraphrag-0.0.3.dist-info/WHEEL
dgraphrag-0.0.3.dist-info/entry_points.txt
dgraphrag-0.0.3.dist-info/top_level.txt
dgraphrag-0.0.3.dist-info/RECORD
