Metadata-Version: 2.4
Name: dgraphrag
Version: 0.0.3
Summary: End-to-end GraphRAG toolkit that takes you from raw documents to a knowledge graph and then to retrieval-augmented generation (RAG) with large language models.
Author-email: Longtao Wu <eustancewu@gmail.com>
Maintainer-email: Longtao Wu <eustancewu@gmail.com>
License: MIT License
Project-URL: Homepage, https://github.com/eust-w/dgraphrag
Project-URL: Repository, https://github.com/eust-w/dgraphrag
Project-URL: Issues, https://github.com/eust-w/dgraphrag/issues
Keywords: graph,rag,knowledge-graph,retrieval,llm
Classifier: Programming Language :: Python :: 3
Classifier: Programming Language :: Python :: 3 :: Only
Classifier: License :: OSI Approved :: MIT License
Classifier: Intended Audience :: Developers
Classifier: Topic :: Scientific/Engineering :: Artificial Intelligence
Requires-Python: >=3.9
License-File: LICENSE
Requires-Dist: networkx>=2.8
Requires-Dist: pydantic>=2.5
Provides-Extra: neo4j
Requires-Dist: neo4j>=5.0; extra == "neo4j"
Provides-Extra: arangodb
Requires-Dist: python-arango>=7.5; extra == "arangodb"
Provides-Extra: tigergraph
Requires-Dist: pyTigerGraph>=1.0; extra == "tigergraph"
Provides-Extra: vector
Requires-Dist: faiss-cpu>=1.7; extra == "vector"
Provides-Extra: spacy
Requires-Dist: spacy>=3.7; extra == "spacy"
Provides-Extra: stanza
Requires-Dist: stanza>=1.7; extra == "stanza"
Provides-Extra: openai
Requires-Dist: openai>=1.6; extra == "openai"
Provides-Extra: dev
Requires-Dist: pytest>=7.0; extra == "dev"
Requires-Dist: ruff>=0.4; extra == "dev"
Requires-Dist: black>=24.4; extra == "dev"
Dynamic: license-file
